es_odm/__init__.py
es_odm/document.py
es_odm/field.py
es_odm/model.py
es_odm/version.py
es_odm-0.0.6.dist-info/LICENSE
es_odm-0.0.6.dist-info/METADATA
es_odm-0.0.6.dist-info/WHEEL
es_odm-0.0.6.dist-info/top_level.txt
es_odm-0.0.6.dist-info/RECORD
